{"data":{"page":{"id":"670c6db8-8383-54c6-bf20-988a6bd46fbb","html":"<p>You can subscribe to the blog via <a href=\"/rss.xml\">RSS feed</a> or by <a href=\"http://eepurl.com/bgk17b\">email</a>.</p>\n<p>If you are interested in hiring my services, please <a href=\"/hire\">check my current status</a>.</p>\n<p>For anything else, you can reach me by:</p>\n<ul>\n<li>Email: hello [@] joanmira [.] com</li>\n<li><a href=\"http://linkedin.com/in/joanmira/\">LinkedIn</a></li>\n<li><a href=\"http://twitter.com/gazpachu\">Twitter</a></li>\n<li><a href=\"http://github.com/gazpachu\">Github</a></li>\n<li><a href=\"http://codepen.io/gazpachu/\">CodePen</a></li>\n<li><a href=\"https://www.hackerrank.com/gazpachu\">HackerRank</a></li>\n</ul>","fields":{"prefix":"/"},"frontmatter":{"title":"Contact","cover":null}}},"pageContext":{"slug":"//contact/","source":"pages"}}